visiumhd_utils/__init__.py
visiumhd_utils/destripe.py
visiumhd_utils/qc_plot.py
visiumhd_utils/read_data.py
visiumhd_utils/write_data.py
visiumhd_utils-0.2.2.dist-info/licenses/LICENSE.txt
visiumhd_utils-0.2.2.dist-info/METADATA
visiumhd_utils-0.2.2.dist-info/WHEEL
visiumhd_utils-0.2.2.dist-info/top_level.txt
visiumhd_utils-0.2.2.dist-info/RECORD
