Metadata-Version: 2.4
Name: visiumhd-utils
Version: 0.2.2
Summary: Tools for pre-processing and visualizing Visium HD spatial transcriptomics data.
Home-page: https://github.com/danielchen05/visiumhd_utils
Author: Daniel Chen
Author-email: danielchenxingyi@gmail.com
License: MIT
Project-URL: Documentation, https://pyscaffold.org/
Platform: any
Classifier: Development Status :: 4 - Beta
Classifier: Programming Language :: Python
Requires-Python: >=3.8
License-File: LICENSE.txt
Requires-Dist: importlib-metadata; python_version < "3.8"
Requires-Dist: scanpy
Requires-Dist: matplotlib
Requires-Dist: numpy
Requires-Dist: spatialdata
Requires-Dist: spatialdata-plot
Requires-Dist: spatialdata-io
Provides-Extra: testing
Requires-Dist: setuptools; extra == "testing"
Requires-Dist: pytest; extra == "testing"
Requires-Dist: pytest-cov; extra == "testing"
Dynamic: license-file
